nonebot_plugin_simplemusic/__init__.py
nonebot_plugin_simplemusic/data_source.py
nonebot_plugin_simplemusic-0.1.6.dist-info/LICENSE
nonebot_plugin_simplemusic-0.1.6.dist-info/METADATA
nonebot_plugin_simplemusic-0.1.6.dist-info/WHEEL
nonebot_plugin_simplemusic-0.1.6.dist-info/RECORD
