Metadata-Version: 2.1
Name: nonebot-plugin-simplemusic
Version: 0.1.6
Summary: 适用于 Nonebot2 的点歌插件
Home-page: https://github.com/noneplugin/nonebot-plugin-simplemusic
License: MIT
Author: meetwq
Author-email: meetwq@gmail.com
Requires-Python: >=3.8,<4.0
Classifier: License :: OSI Approved :: MIT License
Classifier: Programming Language :: Python :: 3
Classifier: Programming Language :: Python :: 3.8
Classifier: Programming Language :: Python :: 3.9
Classifier: Programming Language :: Python :: 3.10
Classifier: Programming Language :: Python :: 3.11
Requires-Dist: httpx (>=0.19.0)
Requires-Dist: nonebot-adapter-onebot (>=2.0.0-beta.1,<3.0.0)
Requires-Dist: nonebot2 (>=2.0.0-beta.4,<3.0.0)
Project-URL: Repository, https://github.com/noneplugin/nonebot-plugin-simplemusic
